{"openapi":"3.1.0","info":{"title":"Weather API","description":"API for querying Ambient Weather data","version":"1.0.0"},"paths":{"/":{"get":{"summary":"Read Root","description":"Root endpoint with API information","operationId":"read_root__get","responses":{"200":{"description":"Successful Response","content":{"application/json":{"schema":{}}}}}}},"/weather":{"get":{"summary":"Get Weather Data","description":"Query weather data from the database\n\nParameters:\n- limit: Maximum number of records (1-1000, default: 100)\n- offset: Number of records to skip (for pagination)\n- start_date: Filter by start date (YYYY-MM-DD format)\n- end_date: Filter by end date (YYYY-MM-DD format)\n- order: Sort order - 'asc' or 'desc' (default: desc)","operationId":"get_weather_data_weather_get","parameters":[{"name":"limit","in":"query","required":false,"schema":{"type":"integer","maximum":1000,"minimum":1,"description":"Maximum number of records to return","default":100,"title":"Limit"},"description":"Maximum number of records to return"},{"name":"offset","in":"query","required":false,"schema":{"type":"integer","minimum":0,"description":"Number of records to skip","default":0,"title":"Offset"},"description":"Number of records to skip"},{"name":"start_date","in":"query","required":false,"schema":{"anyOf":[{"type":"string"},{"type":"null"}],"description":"Start date (ISO format: YYYY-MM-DD)","title":"Start Date"},"description":"Start date (ISO format: YYYY-MM-DD)"},{"name":"end_date","in":"query","required":false,"schema":{"anyOf":[{"type":"string"},{"type":"null"}],"description":"End date (ISO format: YYYY-MM-DD)","title":"End Date"},"description":"End date (ISO format: YYYY-MM-DD)"},{"name":"order","in":"query","required":false,"schema":{"type":"string","pattern":"^(asc|desc)$","description":"Sort order by date (asc or desc)","default":"desc","title":"Order"},"description":"Sort order by date (asc or desc)"}],"responses":{"200":{"description":"Successful Response","content":{"application/json":{"schema":{"type":"array","items":{"$ref":"#/components/schemas/WeatherData"},"title":"Response Get Weather Data Weather Get"}}}},"422":{"description":"Validation Error","content":{"application/json":{"schema":{"$ref":"#/components/schemas/HTTPValidationError"}}}}}}},"/weather/latest":{"get":{"summary":"Get Latest Weather","description":"Get the most recent weather data reading","operationId":"get_latest_weather_weather_latest_get","responses":{"200":{"description":"Successful Response","content":{"application/json":{"schema":{"$ref":"#/components/schemas/WeatherData"}}}}}}},"/weather/stats":{"get":{"summary":"Get Database Stats","description":"Get statistics about the weather database","operationId":"get_database_stats_weather_stats_get","responses":{"200":{"description":"Successful Response","content":{"application/json":{"schema":{"$ref":"#/components/schemas/DatabaseStats"}}}}}}},"/api/health":{"get":{"summary":"Health Check","description":"Health check endpoint for monitoring","operationId":"health_check_api_health_get","responses":{"200":{"description":"Successful Response","content":{"application/json":{"schema":{}}}}}}},"/api/weather/latest":{"get":{"summary":"Api Get Latest Weather","description":"Get the latest weather readings (API route)","operationId":"api_get_latest_weather_api_weather_latest_get","parameters":[{"name":"limit","in":"query","required":false,"schema":{"type":"integer","maximum":10000,"minimum":1,"default":100,"title":"Limit"}}],"responses":{"200":{"description":"Successful Response","content":{"application/json":{"schema":{}}}},"422":{"description":"Validation Error","content":{"application/json":{"schema":{"$ref":"#/components/schemas/HTTPValidationError"}}}}}}},"/api/weather/range":{"get":{"summary":"Api Get Weather Range","description":"Get weather data within a date range (API route)","operationId":"api_get_weather_range_api_weather_range_get","parameters":[{"name":"start_date","in":"query","required":false,"schema":{"anyOf":[{"type":"string"},{"type":"null"}],"title":"Start Date"}},{"name":"end_date","in":"query","required":false,"schema":{"anyOf":[{"type":"string"},{"type":"null"}],"title":"End Date"}},{"name":"limit","in":"query","required":false,"schema":{"type":"integer","maximum":10000,"minimum":1,"default":1000,"title":"Limit"}}],"responses":{"200":{"description":"Successful Response","content":{"application/json":{"schema":{}}}},"422":{"description":"Validation Error","content":{"application/json":{"schema":{"$ref":"#/components/schemas/HTTPValidationError"}}}}}}},"/api/weather/stats":{"get":{"summary":"Api Get Stats","description":"Get database statistics (API route)","operationId":"api_get_stats_api_weather_stats_get","responses":{"200":{"description":"Successful Response","content":{"application/json":{"schema":{}}}}}}}},"components":{"schemas":{"DatabaseStats":{"properties":{"total_records":{"type":"integer","title":"Total Records"},"min_date":{"anyOf":[{"type":"string"},{"type":"null"}],"title":"Min Date"},"max_date":{"anyOf":[{"type":"string"},{"type":"null"}],"title":"Max Date"},"date_range_days":{"anyOf":[{"type":"integer"},{"type":"null"}],"title":"Date Range Days"}},"type":"object","required":["total_records"],"title":"DatabaseStats","description":"Response model for database statistics"},"HTTPValidationError":{"properties":{"detail":{"items":{"$ref":"#/components/schemas/ValidationError"},"type":"array","title":"Detail"}},"type":"object","title":"HTTPValidationError"},"ValidationError":{"properties":{"loc":{"items":{"anyOf":[{"type":"string"},{"type":"integer"}]},"type":"array","title":"Location"},"msg":{"type":"string","title":"Message"},"type":{"type":"string","title":"Error Type"}},"type":"object","required":["loc","msg","type"],"title":"ValidationError"},"WeatherData":{"properties":{"id":{"type":"integer","title":"Id"},"dateutc":{"type":"integer","title":"Dateutc"},"date":{"type":"string","title":"Date"},"tempf":{"anyOf":[{"type":"number"},{"type":"null"}],"title":"Tempf"},"feelsLike":{"anyOf":[{"type":"number"},{"type":"null"}],"title":"Feelslike"},"dewPoint":{"anyOf":[{"type":"number"},{"type":"null"}],"title":"Dewpoint"},"tempinf":{"anyOf":[{"type":"number"},{"type":"null"}],"title":"Tempinf"},"humidity":{"anyOf":[{"type":"integer"},{"type":"null"}],"title":"Humidity"},"humidityin":{"anyOf":[{"type":"integer"},{"type":"null"}],"title":"Humidityin"},"baromrelin":{"anyOf":[{"type":"number"},{"type":"null"}],"title":"Baromrelin"},"baromabsin":{"anyOf":[{"type":"number"},{"type":"null"}],"title":"Baromabsin"},"windspeedmph":{"anyOf":[{"type":"number"},{"type":"null"}],"title":"Windspeedmph"},"windgustmph":{"anyOf":[{"type":"number"},{"type":"null"}],"title":"Windgustmph"},"winddir":{"anyOf":[{"type":"integer"},{"type":"null"}],"title":"Winddir"},"maxdailygust":{"anyOf":[{"type":"number"},{"type":"null"}],"title":"Maxdailygust"},"hourlyrainin":{"anyOf":[{"type":"number"},{"type":"null"}],"title":"Hourlyrainin"},"dailyrainin":{"anyOf":[{"type":"number"},{"type":"null"}],"title":"Dailyrainin"},"weeklyrainin":{"anyOf":[{"type":"number"},{"type":"null"}],"title":"Weeklyrainin"},"monthlyrainin":{"anyOf":[{"type":"number"},{"type":"null"}],"title":"Monthlyrainin"},"totalrainin":{"anyOf":[{"type":"number"},{"type":"null"}],"title":"Totalrainin"},"solarradiation":{"anyOf":[{"type":"number"},{"type":"null"}],"title":"Solarradiation"},"uv":{"anyOf":[{"type":"integer"},{"type":"null"}],"title":"Uv"},"battout":{"anyOf":[{"type":"integer"},{"type":"null"}],"title":"Battout"},"battin":{"anyOf":[{"type":"integer"},{"type":"null"}],"title":"Battin"},"raw_json":{"anyOf":[{"type":"string"},{"type":"null"}],"title":"Raw Json"}},"type":"object","required":["id","dateutc","date"],"title":"WeatherData","description":"Response model for weather data records"}}}}